understat_package/__init__.py
understat_package/function_package.py
understat_package-0.3.dist-info/METADATA
understat_package-0.3.dist-info/WHEEL
understat_package-0.3.dist-info/top_level.txt
understat_package-0.3.dist-info/RECORD
