Metadata-Version: 2.1
Name: understat-package
Version: 0.3
Summary: A Python package to API Data understat.com/
Home-page: UNKNOWN
Author: author
Author-email: ing.lucasbracamonte@gmail.com
License: UNKNOWN
Platform: UNKNOWN
Requires-Dist: pandas
Requires-Dist: sqlalchemy
Requires-Dist: mysql-connector
